LabJackPython.py
Modbus.py
u12.py
u3.py
u6.py
ue9.py
LabJackPython-2.1.0.dist-info/LICENSE
LabJackPython-2.1.0.dist-info/METADATA
LabJackPython-2.1.0.dist-info/WHEEL
LabJackPython-2.1.0.dist-info/top_level.txt
LabJackPython-2.1.0.dist-info/RECORD
