Metadata-Version: 2.1
Name: LabJackPython
Version: 2.1.0
Summary: The LabJack Python modules for the LabJack U3, U6, UE9 and U12.
Home-page: https://labjack.com/support/software/examples/ud/labjackpython
Author: LabJack Corporation
Author-email: support@labjack.com
Maintainer: LabJack Corporation
Maintainer-email: support@labjack.com
License: MIT X11
Classifier: Development Status :: 5 - Production/Stable
Classifier: Environment :: Console
Classifier: Intended Audience :: Developers
Classifier: License :: OSI Approved :: MIT License
Classifier: Operating System :: MacOS :: MacOS X
Classifier: Operating System :: Microsoft :: Windows
Classifier: Operating System :: POSIX :: Linux
Classifier: Programming Language :: Python
Classifier: Programming Language :: Python :: 2
Classifier: Programming Language :: Python :: 2.7
Classifier: Programming Language :: Python :: 3
Classifier: Programming Language :: Python :: 3.3
Classifier: Programming Language :: Python :: 3.4
Classifier: Programming Language :: Python :: 3.5
Classifier: Programming Language :: Python :: 3.6
Classifier: Programming Language :: Python :: 3.7
Classifier: Programming Language :: Python :: 3.8
Classifier: Topic :: Software Development
Classifier: Topic :: Software Development :: Embedded Systems
Classifier: Topic :: System :: Hardware
License-File: LICENSE
